odoo/addons/partner_fax/README.rst
odoo/addons/partner_fax/__init__.py
odoo/addons/partner_fax/__manifest__.py
odoo/addons/partner_fax/i18n/de.po
odoo/addons/partner_fax/i18n/es.po
odoo/addons/partner_fax/i18n/fr.po
odoo/addons/partner_fax/i18n/he.po
odoo/addons/partner_fax/i18n/hr_HR.po
odoo/addons/partner_fax/i18n/it.po
odoo/addons/partner_fax/i18n/nl.po
odoo/addons/partner_fax/i18n/partner_fax.pot
odoo/addons/partner_fax/i18n/pt_BR.po
odoo/addons/partner_fax/i18n/sl.po
odoo/addons/partner_fax/i18n/zh_CN.po
odoo/addons/partner_fax/models/__init__.py
odoo/addons/partner_fax/models/res_partner.py
odoo/addons/partner_fax/readme/CONTRIBUTORS.rst
odoo/addons/partner_fax/readme/DESCRIPTION.rst
odoo/addons/partner_fax/readme/USAGE.rst
odoo/addons/partner_fax/static/description/icon.png
odoo/addons/partner_fax/static/description/index.html
odoo/addons/partner_fax/views/res_partner.xml
odoo14_addon_partner_fax-14.0.1.0.1.dev5.dist-info/METADATA
odoo14_addon_partner_fax-14.0.1.0.1.dev5.dist-info/WHEEL
odoo14_addon_partner_fax-14.0.1.0.1.dev5.dist-info/top_level.txt
odoo14_addon_partner_fax-14.0.1.0.1.dev5.dist-info/RECORD
